ghana_nlp/__init__.py
ghana_nlp/api.py
The_GhanaNLP_python_library-0.1.0.dist-info/LICENSE
The_GhanaNLP_python_library-0.1.0.dist-info/METADATA
The_GhanaNLP_python_library-0.1.0.dist-info/WHEEL
The_GhanaNLP_python_library-0.1.0.dist-info/top_level.txt
The_GhanaNLP_python_library-0.1.0.dist-info/RECORD
