Metadata-Version: 2.1
Name: The-GhanaNLP-python-library
Version: 0.1.0
Summary: A Python library for interacting with the GhanaNLP API
Home-page: https://pnlarbi.vercel.app/
Author: Prince Larbi
Author-email: phiddyconcept@gmail.com
Classifier: Programming Language :: Python :: 3
Classifier: License :: OSI Approved :: MIT License
Classifier: Operating System :: OS Independent
Requires-Python: >=3.6
License-File: LICENSE
Requires-Dist: requests
